rqse/__init__.py
rqse/client.py
rqse/messaging.py
rqse-0.5.3.dist-info/METADATA
rqse-0.5.3.dist-info/WHEEL
rqse-0.5.3.dist-info/top_level.txt
rqse-0.5.3.dist-info/RECORD
