Metadata-Version: 2.1
Name: rqse
Version: 0.5.3
Summary: RQse: Queued System Events for Redis
Home-page: https://github.com/alexmilowski/rqse
Author: Alex Miłowski
Author-email: alex@milowski.com
License: Apache License 2.0
Requires-Dist: redis
